{
  "document_classification": {
    "primary_type": "financial",
    "specific_type": "statement_of_earnings",
    "confidence": 0.98,
    "supported_tabs": [
      "tab1_content",
      "tab2_summary",
      "tab3_tables",
      "semantic_search"
    ],
    "processing_timestamp": "2025-07-22T08:28:49.512329Z"
  },
  "tab1_content": {
    "fields_and_values": {
      "Statement of Earnings": {
        "value": "Statement of Earnings",
        "bbox": {
          "x": 80,
          "y": 45,
          "width": 280,
          "height": 38
        },
        "confidence": 0.97
      },
      "For the period ended": {
        "value": "For the period ended June 30, 2023",
        "bbox": {
          "x": 90,
          "y": 98,
          "width": 390,
          "height": 30
        },
        "confidence": 0.95
      },
      "Revenue Heading": {
        "value": "Revenue",
        "bbox": {
          "x": 90,
          "y": 150,
          "width": 125,
          "height": 32
        },
        "confidence": 0.93
      },
      "Sales": {
        "value": "$50,000",
        "bbox": {
          "x": 400,
          "y": 198,
          "width": 100,
          "height": 23
        },
        "confidence": 0.96
      },
      "Interest Income": {
        "value": "$2,000",
        "bbox": {
          "x": 400,
          "y": 239,
          "width": 90,
          "height": 21
        },
        "confidence": 0.96
      },
      "Expenses Heading": {
        "value": "Expenses",
        "bbox": {
          "x": 90,
          "y": 285,
          "width": 150,
          "height": 34
        },
        "confidence": 0.94
      },
      "Salary": {
        "value": "$25,000",
        "bbox": {
          "x": 400,
          "y": 334,
          "width": 100,
          "height": 19
        },
        "confidence": 0.96
      },
      "Rent": {
        "value": "$5,000",
        "bbox": {
          "x": 400,
          "y": 374,
          "width": 90,
          "height": 19
        },
        "confidence": 0.95
      },
      "Utilities": {
        "value": "$2,500",
        "bbox": {
          "x": 400,
          "y": 414,
          "width": 94,
          "height": 19
        },
        "confidence": 0.94
      },
      "Total Expenses": {
        "value": "$32,500",
        "bbox": {
          "x": 400,
          "y": 459,
          "width": 110,
          "height": 22
        },
        "confidence": 0.96
      },
      "Net Income": {
        "value": "$19,500",
        "bbox": {
          "x": 400,
          "y": 520,
          "width": 110,
          "height": 23
        },
        "confidence": 0.96
      }
    },
    "financial_dashboard": {
      "total_revenue": {
        "value": "$52,000",
        "confidence": 0.96
      },
      "total_expenses": {
        "value": "$32,500",
        "confidence": 0.96
      },
      "net_income": {
        "value": "$19,500",
        "confidence": 0.96
      }
    },
    "form_fields": {},
    "legal_summary": {},
    "general_summary": {
      "period": {
        "value": "For the period ended June 30, 2023",
        "confidence": 0.95
      },
      "document_title": {
        "value": "Statement of Earnings",
        "confidence": 0.97
      }
    }
  },
  "tab2_summary_insights": {
    "executive_summary": {
      "main_purpose": "The primary purpose of this document is to provide a summary of financial performance, specifically outlining revenues, expenses, and net income for the period ended June 30, 2023.",
      "key_parties": [
        "Company management",
        "Shareholders",
        "Finance department",
        "External auditors"
      ],
      "critical_information": [
        "Sales: $50,000",
        "Interest Income: $2,000",
        "Salary Expenses: $25,000",
        "Rent: $5,000",
        "Utilities: $2,500",
        "Total Expenses: $32,500",
        "Net Income: $19,500"
      ],
      "action_items": [
        "Review expense allocations for efficiency",
        "Verify supporting documentation for revenues and expenses",
        "Prepare comparative analysis for previous periods",
        "Ensure final approval and sign-off"
      ],
      "time_sensitive_elements": [
        "Period end date: June 30, 2023",
        "Recommended reporting/filing deadline dependent on internal policy"
      ],
      "document_status": "complete"
    },
    "detailed_analysis": {
      "comprehensive_overview": "This Statement of Earnings provides a concise financial summary for the period ending June 30, 2023. It details the revenue streams, including both sales and interest income, and outlines major expense categories such as salary, rent, and utilities. The statement calculates total expenses and derives net income, offering a snapshot of the entity's profitability for the specified period. The high confidence levels in text extraction and structured presentation of financial data contribute to the reliability of the analysis.\\u0022 \\nThe document is structured with clear headings, indicating revenue and expenses sections, and provides line-item values for significant income and cost drivers. The inclusion of both operational (sales) and non-operational (interest income) revenue sources reflects a comprehensive approach to financial reporting. Expense details are broken down by major categories, and the net income calculation appears consistent with the presented figures. \\nFrom a business standpoint, the document highlights a positive net income, which demonstrates operational profitability for the period. The sales figure is substantially higher than total expenses, suggesting effective cost control. The relative proportions of salary, rent, and utilities expenses also reveal that personnel costs are the largest overhead, which may warrant further assessment for optimization. \\nOverall, this statement holds significance for management decision-making, financial transparency, and potential compliance with reporting requirements. It may also be leveraged for performance evaluation, budgeting, or reporting to stakeholders. The clarity and structure of this document suggest robust internal controls and diligent financial management.",
      "section_breakdown": [
        {
          "section_name": "Header",
          "content_summary": "Contains the document title and reporting period.",
          "key_insights": [
            "Clearly states scope and time frame",
            "Essential for context and period-based analysis"
          ],
          "data_quality": "High clarity; purpose and period are unambiguous."
        },
        {
          "section_name": "Body",
          "content_summary": "Details revenue sources, expense line items, totals, and net income through a mix of headings, table cells, and amounts.",
          "key_insights": [
            "Revenue and expenses are itemized",
            "Net income is derived and aligns with input values",
            "High visibility into major cost drivers"
          ],
          "data_quality": "Very high; amounts and categories are clearly presented and consistent."
        },
        {
          "section_name": "Table",
          "content_summary": "Tabular presentation of all financial items, summarizing key figures for the period.",
          "key_insights": [
            "Consolidated view enhances readability",
            "Easy comparison of revenues vs. expenses"
          ],
          "data_quality": "Structured and highly legible; matches narrative content."
        },
        {
          "section_name": "Footer",
          "content_summary": "No explicit footer identified; page completeness inferred from absence of further content.",
          "key_insights": [
            "No end notes or disclaimers observed",
            "Potential area to include sign-off or approval in future versions"
          ],
          "data_quality": "Not applicable; no data present."
        }
      ]
    },
    "business_insights": {
      "compliance_status": "The document generally aligns with standard financial reporting requirements and presents figures consistent with basic income statement formats. However, there is no indication of external verification or audit. Overall, it appears compliant for internal or preliminary purposes.",
      "risk_indicators": [
        "No evidence of external audit or third-party verification",
        "Limited breakdown of expense categories beyond salary, rent, and utilities",
        "Absence of supporting notes or disclosures"
      ],
      "opportunities": [
        "Positive net income indicates strong operational performance",
        "Potential to further analyze salary expenses for efficiency improvements",
        "Consistent reporting format facilitates benchmarking and trend analysis"
      ],
      "data_confidence": "High confidence in data accuracy and completeness based on extraction quality and data structure"
    },
    "processing_metadata": {
      "extraction_confidence": 0.92,
      "missing_information": [
        "Absence of entity name and preparer information",
        "No detail on supporting schedules or notes",
        "No breakdown of other possible costs or revenues",
        "Filing or approval status missing"
      ],
      "data_completeness_percentage": 95,
      "recommendations": [
        "Include company/entity name and signatory for authentication",
        "Provide supporting notes or explanations for material financial entries",
        "Expand breakdown of variable and fixed costs if available",
        "Confirm external audit or approval for regulatory compliance"
      ]
    }
  },
  "tab3_tables": {
    "identified_tables": [
      {
        "table_id": "table_1",
        "table_type": "other",
        "table_title": "Statement of Earnings Table",
        "bbox": {
          "x": 100,
          "y": 190,
          "width": 430,
          "height": 360
        },
        "column_headers": [
          "Description",
          "Amount"
        ],
        "rows": [
          {
            "Description": "Sales",
            "Amount": "$50,000"
          },
          {
            "Description": "Interest Income",
            "Amount": "$2,000"
          },
          {
            "Description": "Salary",
            "Amount": "$25,000"
          },
          {
            "Description": "Rent",
            "Amount": "$5,000"
          },
          {
            "Description": "Utilities",
            "Amount": "$2,500"
          },
          {
            "Description": "Total Expenses",
            "Amount": "$32,500"
          },
          {
            "Description": "Net Income",
            "Amount": "$19,500"
          }
        ],
        "table_metadata": {
          "total_rows": 7,
          "total_columns": 2,
          "has_totals_row": true,
          "data_types": {
            "Description": "text",
            "Amount": "currency"
          }
        }
      }
    ],
    "table_relationships": [
      {
        "primary_table": "table_1",
        "related_fields": [
          "Total Expenses",
          "Net Income"
        ],
        "calculation_validation": "Total Expenses validated ($25,000 + $5,000 + $2,500 = $32,500); Net Income validated ($50,000 + $2,000 - $32,500 = $19,500)"
      }
    ]
  }
}